bookmarkdown/__init__.py
bookmarkdown/btm.py
bookmarkdown-0.1.1.dist-info/entry_points.txt
bookmarkdown-0.1.1.dist-info/LICENSE
bookmarkdown-0.1.1.dist-info/WHEEL
bookmarkdown-0.1.1.dist-info/METADATA
bookmarkdown-0.1.1.dist-info/RECORD
