Metadata-Version: 2.1
Name: bookmarkdown
Version: 0.1.1
Summary: Parse your browser's exported HTML bookmark file to Markdown.
Home-page: https://github.com/yannickperrenet/bookmarkdown
License: MIT
Keywords: bookmarks,markdown,parser
Author: Yannick Perrenet
Author-email: yannickperrenet+bookmarkdown@gmail.com
Requires-Python: >=3.7,<4.0
Classifier: Development Status :: 3 - Alpha
Classifier: Environment :: Console
Classifier: Intended Audience :: Developers
Classifier: License :: OSI Approved :: MIT License
Classifier: Operating System :: Unix
Classifier: Programming Language :: Python :: 3
Classifier: Programming Language :: Python :: 3.7
Classifier: Programming Language :: Python :: 3.8
Classifier: Programming Language :: Python :: 3.9
Classifier: Topic :: Utilities
